s3_sync/__init__.py
s3_sync/controllers/__init__.py
s3_sync/controllers/sync_controller.py
s3_sync/schemas/__init__.py
s3_sync/schemas/s3_detail_object.py
s3_sync/schemas/storage.py
s3_sync/schemas/sync_object.py
s3_sync/schemas/sync_storage.py
s3_sync/services/__init__.py
s3_sync/services/s3_services.py
s3_sync/utils/__init__.py
s3_sync/utils/utils.py
s3_sync-0.3.1.dist-info/LICENSE
s3_sync-0.3.1.dist-info/METADATA
s3_sync-0.3.1.dist-info/WHEEL
s3_sync-0.3.1.dist-info/entry_points.txt
s3_sync-0.3.1.dist-info/top_level.txt
s3_sync-0.3.1.dist-info/RECORD
