Metadata-Version: 2.1
Name: s3-sync
Version: 0.3.1
Summary: Sync s3 from one source to another place
Home-page: https://github.com/FerdinaKusumah/s3-sync
Author: Ferdina Kusumah
Author-email: ferdina.kusumah@gmail.com
License: MIT
Platform: UNKNOWN
Classifier: License :: OSI Approved :: MIT License
Classifier: Programming Language :: Python :: 3.7
Classifier: Programming Language :: Python :: 3.8
Classifier: Programming Language :: Python :: 3.9
License-File: LICENSE
Requires-Dist: boto3 (==1.21.42)
Requires-Dist: pydantic (==1.9.0)
Requires-Dist: tqdm (==4.64.0)
Requires-Dist: PyYAML (==6.0)
